[
  {
    "name": "Bentley Continental Gt",
    "brand": "Mini GT",
    "category": "Imported",
    "subcategory": "Imported",
    "price": 1700,
    "image": "/images/products/bentley-continental-gt.jpeg",
    "originalPrice": 1700,
    "stockStatus": "In Stock",
    "scale": "1:64",
    "imported": false,
    "carded": true,
    "series": "Custom Upload",
    "releaseYear": 2026,
    "wave": "Custom",
    "vehicleType": "Supercar",
    "featured": true,
    "newArrival": true,
    "popularity": 100,
    "packagingType": "Standard Custom",
    "color": "standard"
  },
  {
    "name": "BMW M3 | Premium | Euro Speed | E46",
    "brand": "Hot Wheels",
    "category": "Premium",
    "subcategory": "Premium",
    "price": 1299,
    "image": "/images/products/bmw-m3-premium-euro-speed-e46.png",
    "originalPrice": 1299,
    "stockStatus": "In Stock",
    "scale": "1:64",
    "imported": false,
    "carded": true,
    "series": "Custom Upload",
    "releaseYear": 2026,
    "wave": "Custom",
    "vehicleType": "Classic",
    "featured": true,
    "newArrival": true,
    "popularity": 100,
    "packagingType": "Standard Custom",
    "color": "standard"
  },
  {
    "name": "Nissan Skyline lbwk ER34 Red",
    "brand": "Mini GT",
    "category": "Imported",
    "subcategory": "Imported",
    "price": 1900,
    "image": "/images/products/nissan-skyline-lbwk-er34-red.jpeg",
    "originalPrice": 1900,
    "stockStatus": "In Stock",
    "scale": "1:64",
    "imported": false,
    "carded": true,
    "series": "Custom Upload",
    "releaseYear": 2026,
    "wave": "Custom",
    "vehicleType": "JDM",
    "featured": true,
    "newArrival": true,
    "popularity": 100,
    "packagingType": "Standard Custom",
    "color": "standard"
  },
  {
    "name": "BMW M3 | Premium | Euro Speed | E46",
    "brand": "Hot Wheels",
    "category": "Premium",
    "subcategory": "Premium",
    "price": 129997,
    "originalPrice": 129997,
    "stockStatus": "In Stock",
    "scale": "1:64",
    "imported": false,
    "carded": true,
    "series": "Custom Upload",
    "releaseYear": 2026,
    "wave": "Custom",
    "vehicleType": "Classic",
    "featured": true,
    "newArrival": true,
    "popularity": 100,
    "packagingType": "Standard Custom",
    "color": "standard"
  },
  {
    "name": "Hot Wheels Boulevard Nissan Skyline GT-R (BNR34)",
    "brand": "Hot Wheels",
    "category": "Boulevard",
    "subcategory": "Boulevard",
    "price": 899,
    "originalPrice": 999,
    "stockStatus": "In Stock",
    "scale": "1:64",
    "imported": true,
    "carded": true,
    "series": "Boulevard",
    "releaseYear": 2024,
    "wave": "Wave 7",
    "vehicleType": "JDM",
    "featured": true,
    "newArrival": true,
    "popularity": 98,
    "packagingType": "Carded premium blister",
    "color": "midnight-blue"
  },
  {
    "name": "Hot Wheels Premium Mercedes-Benz 190E Evolution II",
    "brand": "Hot Wheels",
    "category": "Premium",
    "subcategory": "Car Culture",
    "price": 849,
    "stockStatus": "In Stock",
    "scale": "1:64",
    "imported": true,
    "carded": true,
    "series": "Car Culture",
    "releaseYear": 2024,
    "wave": "Wave 5",
    "vehicleType": "Race Car",
    "featured": true,
    "popularity": 94,
    "packagingType": "Carded premium blister",
    "color": "silver-arrow"
  },
  {
    "name": "Hot Wheels Mainline Porsche 911 GT3",
    "brand": "Hot Wheels",
    "category": "Mainline",
    "subcategory": "Factory Fresh",
    "price": 199,
    "stockStatus": "In Stock",
    "scale": "1:64",
    "imported": false,
    "carded": true,
    "series": "Factory Fresh",
    "releaseYear": 2024,
    "wave": "Case J",
    "vehicleType": "Supercar",
    "newArrival": true,
    "popularity": 87,
    "packagingType": "Carded mainline blister",
    "color": "white-racer"
  },
  {
    "name": "Hot Wheels Silver Series Toyota Supra Turbo",
    "brand": "Hot Wheels",
    "category": "Silver Series",
    "subcategory": "Silver Series",
    "price": 499,
    "stockStatus": "In Stock",
    "scale": "1:64",
    "imported": false,
    "carded": true,
    "series": "Silver Series",
    "releaseYear": 2024,
    "wave": "Wave 2",
    "vehicleType": "JDM",
    "popularity": 82,
    "packagingType": "Carded collector blister",
    "color": "steel-grey"
  },
  {
    "name": "Hot Wheels Team Transport Pandem Datsun 620",
    "brand": "Hot Wheels",
    "category": "Team Transport",
    "subcategory": "Team Transport",
    "price": 1699,
    "stockStatus": "Pre-order",
    "scale": "1:64",
    "imported": true,
    "carded": true,
    "series": "Team Transport",
    "releaseYear": 2025,
    "wave": "Wave 1",
    "vehicleType": "SUV / Truck",
    "featured": true,
    "popularity": 93,
    "packagingType": "Carded transport pack",
    "color": "race-red"
  },
  {
    "name": "Hot Wheels Pop Culture Back to the Future Time Machine",
    "brand": "Hot Wheels",
    "category": "Pop Culture",
    "subcategory": "Entertainment",
    "price": 899,
    "stockStatus": "In Stock",
    "scale": "1:64",
    "imported": true,
    "carded": true,
    "series": "Pop Culture",
    "releaseYear": 2024,
    "wave": "Wave 3",
    "vehicleType": "Movie / Pop Culture",
    "popularity": 90,
    "packagingType": "Carded premium blister",
    "color": "flux-silver"
  },
  {
    "name": "Hot Wheels Imported Honda Civic EF Kanjo",
    "brand": "Hot Wheels",
    "category": "Imported",
    "subcategory": "J-Imports",
    "price": 579,
    "stockStatus": "Sold Out",
    "scale": "1:64",
    "imported": true,
    "carded": true,
    "series": "Imports Select",
    "releaseYear": 2024,
    "wave": "Case G",
    "vehicleType": "JDM",
    "popularity": 76,
    "packagingType": "Carded import blister",
    "color": "championship-white"
  },
  {
    "name": "Hot Wheels Limited Edition RWB Porsche 930 Aero",
    "brand": "Hot Wheels",
    "category": "Limited Edition",
    "subcategory": "Collector Exclusive",
    "price": 1899,
    "stockStatus": "Pre-order",
    "scale": "1:64",
    "imported": true,
    "carded": true,
    "series": "Collector Exclusive",
    "releaseYear": 2025,
    "wave": "Drop A",
    "vehicleType": "Supercar",
    "featured": true,
    "popularity": 97,
    "packagingType": "Special carded display pack",
    "color": "obsidian-black"
  },
  {
    "name": "Hot Wheels Mainline Mazda RX-7 FD Drift Spec",
    "brand": "Hot Wheels",
    "category": "Mainline",
    "subcategory": "HW J-Imports",
    "price": 219,
    "stockStatus": "In Stock",
    "scale": "1:64",
    "imported": false,
    "carded": true,
    "series": "HW J-Imports",
    "releaseYear": 2024,
    "wave": "Case L",
    "vehicleType": "JDM",
    "newArrival": true,
    "popularity": 84,
    "packagingType": "Carded mainline blister",
    "color": "sunburst-orange"
  },
  {
    "name": "Hot Wheels Premium Ford GT Race Team",
    "brand": "Hot Wheels",
    "category": "Premium",
    "subcategory": "Car Culture",
    "price": 849,
    "stockStatus": "In Stock",
    "scale": "1:64",
    "imported": true,
    "carded": true,
    "series": "Car Culture",
    "releaseYear": 2023,
    "wave": "Wave 6",
    "vehicleType": "Race Car",
    "popularity": 81,
    "packagingType": "Carded premium blister",
    "color": "lemans-blue"
  },
  {
    "name": "Hot Wheels Silver Series Chevrolet Camaro Z28",
    "brand": "Hot Wheels",
    "category": "Silver Series",
    "subcategory": "Silver Series",
    "price": 459,
    "stockStatus": "In Stock",
    "scale": "1:64",
    "imported": false,
    "carded": true,
    "series": "Silver Series",
    "releaseYear": 2024,
    "wave": "Wave 4",
    "vehicleType": "Muscle",
    "popularity": 74,
    "packagingType": "Carded collector blister",
    "color": "silver-mist"
  },
  {
    "name": "Hot Wheels Collector Set JDM Legends 5-Pack",
    "brand": "Hot Wheels",
    "category": "Collector Set",
    "subcategory": "5-Pack",
    "price": 1399,
    "stockStatus": "In Stock",
    "scale": "1:64",
    "imported": false,
    "carded": true,
    "series": "Collector Multipack",
    "releaseYear": 2024,
    "wave": "Set 3",
    "vehicleType": "JDM",
    "popularity": 86,
    "packagingType": "Window box set",
    "color": "graphite"
  },
  {
    "name": "Matchbox 2024 Ford Mustang GTD",
    "brand": "Matchbox",
    "category": "Mainline",
    "subcategory": "Road Fleet",
    "price": 249,
    "stockStatus": "In Stock",
    "scale": "1:64",
    "imported": false,
    "carded": true,
    "series": "Road Fleet",
    "releaseYear": 2024,
    "wave": "Case H",
    "vehicleType": "Muscle",
    "newArrival": true,
    "popularity": 80,
    "packagingType": "Carded blister",
    "color": "performance-blue"
  },
  {
    "name": "Matchbox Moving Parts Toyota Land Cruiser 80",
    "brand": "Matchbox",
    "category": "Premium",
    "subcategory": "Moving Parts",
    "price": 699,
    "stockStatus": "In Stock",
    "scale": "1:64",
    "imported": true,
    "carded": true,
    "series": "Moving Parts",
    "releaseYear": 2024,
    "wave": "Wave 2",
    "vehicleType": "SUV / Truck",
    "featured": true,
    "popularity": 88,
    "packagingType": "Carded deluxe blister",
    "color": "desert-beige"
  },
  {
    "name": "Matchbox Best of Germany Porsche 964 Carrera RS",
    "brand": "Matchbox",
    "category": "Imported",
    "subcategory": "Best Of",
    "price": 749,
    "stockStatus": "In Stock",
    "scale": "1:64",
    "imported": true,
    "carded": true,
    "series": "Best Of Germany",
    "releaseYear": 2024,
    "wave": "Wave 1",
    "vehicleType": "Supercar",
    "popularity": 83,
    "packagingType": "Carded import blister",
    "color": "guards-red"
  },
  {
    "name": "Matchbox Collector Datsun 510 Wagon",
    "brand": "Matchbox",
    "category": "Collector Set",
    "subcategory": "Collectors",
    "price": 899,
    "stockStatus": "In Stock",
    "scale": "1:64",
    "imported": true,
    "carded": true,
    "series": "Collectors",
    "releaseYear": 2023,
    "wave": "Wave 4",
    "vehicleType": "JDM",
    "popularity": 79,
    "packagingType": "Carded collector blister",
    "color": "olive-green"
  },
  {
    "name": "Matchbox Mercedes-Benz Unimog Utility Service",
    "brand": "Matchbox",
    "category": "Mainline",
    "subcategory": "Utility Fleet",
    "price": 229,
    "stockStatus": "In Stock",
    "scale": "1:64",
    "imported": false,
    "carded": true,
    "series": "Utility Fleet",
    "releaseYear": 2024,
    "wave": "Case F",
    "vehicleType": "SUV / Truck",
    "popularity": 71,
    "packagingType": "Carded blister",
    "color": "signal-yellow"
  },
  {
    "name": "Matchbox Jurassic Park Ford Explorer",
    "brand": "Matchbox",
    "category": "Pop Culture",
    "subcategory": "Entertainment",
    "price": 799,
    "stockStatus": "Sold Out",
    "scale": "1:64",
    "imported": true,
    "carded": true,
    "series": "Entertainment",
    "releaseYear": 2023,
    "wave": "Wave 3",
    "vehicleType": "Movie / Pop Culture",
    "popularity": 85,
    "packagingType": "Carded premium blister",
    "color": "park-green"
  },
  {
    "name": "Matchbox Special Edition Honda e Championship White",
    "brand": "Matchbox",
    "category": "Limited Edition",
    "subcategory": "Special Edition",
    "price": 999,
    "stockStatus": "Pre-order",
    "scale": "1:64",
    "imported": true,
    "carded": false,
    "series": "Special Edition",
    "releaseYear": 2025,
    "wave": "Drop 1",
    "vehicleType": "Classic",
    "popularity": 75,
    "packagingType": "Acrylic display box",
    "color": "arctic-white"
  },
  {
    "name": "Matchbox Convoys Mercedes Actros Race Support",
    "brand": "Matchbox",
    "category": "Team Transport",
    "subcategory": "Convoys",
    "price": 1499,
    "stockStatus": "In Stock",
    "scale": "1:64",
    "imported": false,
    "carded": true,
    "series": "Convoys",
    "releaseYear": 2024,
    "wave": "Wave 1",
    "vehicleType": "SUV / Truck",
    "popularity": 77,
    "packagingType": "Carded convoy pack",
    "color": "haulage-red"
  },
  {
    "name": "Majorette Porsche 934 Heritage Edition",
    "brand": "Majorette",
    "category": "Premium",
    "subcategory": "Deluxe",
    "price": 649,
    "stockStatus": "In Stock",
    "scale": "1:64",
    "imported": true,
    "carded": false,
    "series": "Heritage Deluxe",
    "releaseYear": 2024,
    "wave": "Wave 2",
    "vehicleType": "Race Car",
    "newArrival": true,
    "popularity": 84,
    "packagingType": "Window display box",
    "color": "heritage-silver"
  },
  {
    "name": "Majorette Black Edition Nissan GT-R Nismo",
    "brand": "Majorette",
    "category": "Limited Edition",
    "subcategory": "Black Edition",
    "price": 899,
    "stockStatus": "In Stock",
    "scale": "1:64",
    "imported": true,
    "carded": false,
    "series": "Black Edition",
    "releaseYear": 2024,
    "wave": "Wave 1",
    "vehicleType": "JDM",
    "featured": true,
    "popularity": 90,
    "packagingType": "Collector display box",
    "color": "phantom-black"
  },
  {
    "name": "Majorette Japan Series Toyota Hiace Custom",
    "brand": "Majorette",
    "category": "Imported",
    "subcategory": "Japan Series",
    "price": 699,
    "stockStatus": "In Stock",
    "scale": "1:64",
    "imported": true,
    "carded": true,
    "series": "Japan Series",
    "releaseYear": 2024,
    "wave": "Wave 2",
    "vehicleType": "SUV / Truck",
    "popularity": 73,
    "packagingType": "Carded deluxe blister",
    "color": "midnight-grey"
  },
  {
    "name": "Majorette Racing Cars Audi RS e-tron GT",
    "brand": "Majorette",
    "category": "Mainline",
    "subcategory": "Racing Cars",
    "price": 329,
    "stockStatus": "In Stock",
    "scale": "1:64",
    "imported": false,
    "carded": true,
    "series": "Racing Cars",
    "releaseYear": 2024,
    "wave": "Wave 5",
    "vehicleType": "Supercar",
    "popularity": 70,
    "packagingType": "Carded blister",
    "color": "electric-red"
  },
  {
    "name": "Majorette Vintage Porsche 911 Carrera RS",
    "brand": "Majorette",
    "category": "Collector Set",
    "subcategory": "Vintage Collection",
    "price": 799,
    "stockStatus": "Sold Out",
    "scale": "1:64",
    "imported": true,
    "carded": false,
    "series": "Vintage Collection",
    "releaseYear": 2023,
    "wave": "Series 2",
    "vehicleType": "Classic",
    "popularity": 78,
    "packagingType": "Window display box",
    "color": "grand-prix-white"
  },
  {
    "name": "Majorette Tune Ups Mystery Civic Type R",
    "brand": "Majorette",
    "category": "Pre-order",
    "subcategory": "Tune Ups",
    "price": 599,
    "stockStatus": "Pre-order",
    "scale": "1:64",
    "imported": true,
    "carded": false,
    "series": "Tune Ups",
    "releaseYear": 2025,
    "wave": "Series 1",
    "vehicleType": "JDM",
    "popularity": 76,
    "packagingType": "Blind box",
    "color": "rally-red"
  },
  {
    "name": "Majorette Deluxe Ford Bronco Wildtrak",
    "brand": "Majorette",
    "category": "Premium",
    "subcategory": "Deluxe",
    "price": 679,
    "stockStatus": "In Stock",
    "scale": "1:64",
    "imported": false,
    "carded": true,
    "series": "Deluxe",
    "releaseYear": 2024,
    "wave": "Wave 3",
    "vehicleType": "SUV / Truck",
    "popularity": 68,
    "packagingType": "Carded deluxe blister",
    "color": "canyon-orange"
  },
  {
    "name": "Majorette Limited Gift Pack JDM Icons",
    "brand": "Majorette",
    "category": "Collector Set",
    "subcategory": "Gift Pack",
    "price": 1499,
    "stockStatus": "In Stock",
    "scale": "1:64",
    "imported": true,
    "carded": false,
    "series": "Gift Pack",
    "releaseYear": 2024,
    "wave": "Set A",
    "vehicleType": "JDM",
    "popularity": 81,
    "packagingType": "Window gift box",
    "color": "collector-blue"
  },
  {
    "name": "Mini GT LBWK Lamborghini Aventador",
    "brand": "Mini GT",
    "category": "Imported",
    "subcategory": "Liberty Walk",
    "price": 1599,
    "stockStatus": "In Stock",
    "scale": "1:64",
    "imported": true,
    "carded": false,
    "series": "Liberty Walk",
    "releaseYear": 2024,
    "wave": "Drop 6",
    "vehicleType": "Supercar",
    "featured": true,
    "newArrival": true,
    "popularity": 96,
    "packagingType": "Mini GT window box",
    "color": "acid-green"
  },
  {
    "name": "Mini GT Nissan Skyline GT-R Top Secret VR32",
    "brand": "Mini GT",
    "category": "Limited Edition",
    "subcategory": "Top Secret",
    "price": 1699,
    "stockStatus": "Pre-order",
    "scale": "1:64",
    "imported": true,
    "carded": false,
    "series": "Top Secret",
    "releaseYear": 2025,
    "wave": "Drop 1",
    "vehicleType": "JDM",
    "popularity": 95,
    "packagingType": "Mini GT window box",
    "color": "gold-flake"
  },
  {
    "name": "Mini GT Porsche 911 Dakar Shade Green",
    "brand": "Mini GT",
    "category": "Premium",
    "subcategory": "Street",
    "price": 1499,
    "stockStatus": "In Stock",
    "scale": "1:64",
    "imported": true,
    "carded": false,
    "series": "Street",
    "releaseYear": 2024,
    "wave": "Drop 4",
    "vehicleType": "SUV / Truck",
    "popularity": 88,
    "packagingType": "Mini GT window box",
    "color": "shade-green"
  },
  {
    "name": "Mini GT BMW M4 GT3 SPA 24H",
    "brand": "Mini GT",
    "category": "Premium",
    "subcategory": "Motorsport",
    "price": 1549,
    "stockStatus": "In Stock",
    "scale": "1:64",
    "imported": true,
    "carded": false,
    "series": "Motorsport",
    "releaseYear": 2024,
    "wave": "Drop 8",
    "vehicleType": "Race Car",
    "popularity": 86,
    "packagingType": "Mini GT window box",
    "color": "race-livery"
  },
  {
    "name": "Mini GT Pagani Huayra Roadster Blue Carbon",
    "brand": "Mini GT",
    "category": "Imported",
    "subcategory": "Hypercar",
    "price": 1799,
    "stockStatus": "In Stock",
    "scale": "1:64",
    "imported": true,
    "carded": false,
    "series": "Hypercar",
    "releaseYear": 2023,
    "wave": "Drop 11",
    "vehicleType": "Supercar",
    "popularity": 89,
    "packagingType": "Mini GT window box",
    "color": "carbon-blue"
  },
  {
    "name": "Mini GT Kaido Racer Datsun 510 Wagon V2",
    "brand": "Mini GT",
    "category": "Pre-order",
    "subcategory": "Kaido Racer",
    "price": 1749,
    "stockStatus": "Pre-order",
    "scale": "1:64",
    "imported": true,
    "carded": false,
    "series": "Kaido Racer",
    "releaseYear": 2025,
    "wave": "Wave 1",
    "vehicleType": "JDM",
    "popularity": 92,
    "packagingType": "Mini GT collector box",
    "color": "sunset-orange"
  },
  {
    "name": "Mini GT Lamborghini Huracan GT3 EVO2",
    "brand": "Mini GT",
    "category": "Premium",
    "subcategory": "Motorsport",
    "price": 1529,
    "stockStatus": "Sold Out",
    "scale": "1:64",
    "imported": true,
    "carded": false,
    "series": "Motorsport",
    "releaseYear": 2024,
    "wave": "Drop 5",
    "vehicleType": "Race Car",
    "popularity": 87,
    "packagingType": "Mini GT window box",
    "color": "verde-mantis"
  },
  {
    "name": "Mini GT Mercedes-Benz Actros with GT-R Trailer",
    "brand": "Mini GT",
    "category": "Team Transport",
    "subcategory": "Transporters",
    "price": 2899,
    "stockStatus": "In Stock",
    "scale": "1:64",
    "imported": true,
    "carded": false,
    "series": "Transporters",
    "releaseYear": 2024,
    "wave": "Transport 2",
    "vehicleType": "SUV / Truck",
    "popularity": 84,
    "packagingType": "Large collector display box",
    "color": "transport-grey"
  },
  {
    "name": "Pop Race Pandem Civic EG6",
    "brand": "Pop Race",
    "category": "Imported",
    "subcategory": "Pandem",
    "price": 1399,
    "stockStatus": "In Stock",
    "scale": "1:64",
    "imported": true,
    "carded": false,
    "series": "Pandem",
    "releaseYear": 2024,
    "wave": "Series 4",
    "vehicleType": "JDM",
    "featured": true,
    "popularity": 91,
    "packagingType": "Collector display box",
    "color": "championship-yellow"
  },
  {
    "name": "Pop Race Skyline C210 Kaido Racer",
    "brand": "Pop Race",
    "category": "Limited Edition",
    "subcategory": "Kaido Racer",
    "price": 1499,
    "stockStatus": "In Stock",
    "scale": "1:64",
    "imported": true,
    "carded": false,
    "series": "Kaido Racer",
    "releaseYear": 2024,
    "wave": "Series 2",
    "vehicleType": "JDM",
    "popularity": 90,
    "packagingType": "Collector display box",
    "color": "midnight-purple"
  },
  {
    "name": "Pop Race Aston Martin Vantage GT3",
    "brand": "Pop Race",
    "category": "Premium",
    "subcategory": "GT Racing",
    "price": 1429,
    "stockStatus": "In Stock",
    "scale": "1:64",
    "imported": true,
    "carded": false,
    "series": "GT Racing",
    "releaseYear": 2024,
    "wave": "Series 5",
    "vehicleType": "Race Car",
    "popularity": 82,
    "packagingType": "Collector display box",
    "color": "racing-green"
  },
  {
    "name": "Pop Race Singer 964 Carbon Decklid",
    "brand": "Pop Race",
    "category": "Imported",
    "subcategory": "Restomod",
    "price": 1479,
    "stockStatus": "Sold Out",
    "scale": "1:64",
    "imported": true,
    "carded": false,
    "series": "Restomod",
    "releaseYear": 2023,
    "wave": "Series 1",
    "vehicleType": "Classic",
    "popularity": 88,
    "packagingType": "Collector display box",
    "color": "graphite-silver"
  },
  {
    "name": "Pop Race RWB 997 Red Phoenix",
    "brand": "Pop Race",
    "category": "Pre-order",
    "subcategory": "RWB",
    "price": 1529,
    "stockStatus": "Pre-order",
    "scale": "1:64",
    "imported": true,
    "carded": false,
    "series": "RWB",
    "releaseYear": 2025,
    "wave": "Series 1",
    "vehicleType": "Supercar",
    "popularity": 89,
    "packagingType": "Collector display box",
    "color": "phoenix-red"
  },
  {
    "name": "Pop Race Toyota Supra A90 HKS",
    "brand": "Pop Race",
    "category": "Premium",
    "subcategory": "Street Tuner",
    "price": 1399,
    "stockStatus": "In Stock",
    "scale": "1:64",
    "imported": true,
    "carded": false,
    "series": "Street Tuner",
    "releaseYear": 2024,
    "wave": "Series 3",
    "vehicleType": "JDM",
    "popularity": 84,
    "packagingType": "Collector display box",
    "color": "hks-purple"
  },
  {
    "name": "Pop Race LB-Silhouette Works GT Nissan 35GT-RR",
    "brand": "Pop Race",
    "category": "Imported",
    "subcategory": "Liberty Walk",
    "price": 1499,
    "stockStatus": "In Stock",
    "scale": "1:64",
    "imported": true,
    "carded": false,
    "series": "Liberty Walk",
    "releaseYear": 2024,
    "wave": "Series 4",
    "vehicleType": "Supercar",
    "popularity": 86,
    "packagingType": "Collector display box",
    "color": "stealth-grey"
  },
  {
    "name": "Tarmac Works HKS Skyline GT-R",
    "brand": "Tarmac Works",
    "category": "Premium",
    "subcategory": "Global64",
    "price": 1599,
    "stockStatus": "In Stock",
    "scale": "1:64",
    "imported": true,
    "carded": false,
    "series": "Global64",
    "releaseYear": 2024,
    "wave": "Drop 7",
    "vehicleType": "JDM",
    "featured": true,
    "popularity": 94,
    "packagingType": "Collector display box",
    "color": "hks-gradient"
  },
  {
    "name": "Tarmac Works Vertex Toyota Chaser JZX100",
    "brand": "Tarmac Works",
    "category": "Imported",
    "subcategory": "Global64",
    "price": 1549,
    "stockStatus": "In Stock",
    "scale": "1:64",
    "imported": true,
    "carded": false,
    "series": "Global64",
    "releaseYear": 2024,
    "wave": "Drop 6",
    "vehicleType": "JDM",
    "popularity": 87,
    "packagingType": "Collector display box",
    "color": "vertex-white"
  },
  {
    "name": "Tarmac Works Porsche RWB 930 Blackbird",
    "brand": "Tarmac Works",
    "category": "Limited Edition",
    "subcategory": "Hobby64",
    "price": 2199,
    "stockStatus": "Pre-order",
    "scale": "1:64",
    "imported": true,
    "carded": false,
    "series": "Hobby64",
    "releaseYear": 2025,
    "wave": "Drop 2",
    "vehicleType": "Supercar",
    "popularity": 93,
    "packagingType": "Premium acrylic case",
    "color": "blackbird"
  },
  {
    "name": "Tarmac Works Mercedes-AMG GT3 Macau FIA GT Cup",
    "brand": "Tarmac Works",
    "category": "Premium",
    "subcategory": "Motorsport",
    "price": 1649,
    "stockStatus": "In Stock",
    "scale": "1:64",
    "imported": true,
    "carded": false,
    "series": "Motorsport",
    "releaseYear": 2024,
    "wave": "Drop 4",
    "vehicleType": "Race Car",
    "popularity": 83,
    "packagingType": "Collector display box",
    "color": "macau-yellow"
  },
  {
    "name": "Tarmac Works Toyota Land Cruiser Prado Adventure",
    "brand": "Tarmac Works",
    "category": "Imported",
    "subcategory": "Global64",
    "price": 1499,
    "stockStatus": "In Stock",
    "scale": "1:64",
    "imported": true,
    "carded": false,
    "series": "Global64",
    "releaseYear": 2024,
    "wave": "Drop 5",
    "vehicleType": "SUV / Truck",
    "popularity": 80,
    "packagingType": "Collector display box",
    "color": "sandstone"
  },
  {
    "name": "Tarmac Works Ferrari F40 LM Heritage Spec",
    "brand": "Tarmac Works",
    "category": "Collector Set",
    "subcategory": "Heritage Collection",
    "price": 1999,
    "stockStatus": "Sold Out",
    "scale": "1:64",
    "imported": true,
    "carded": false,
    "series": "Heritage Collection",
    "releaseYear": 2023,
    "wave": "Set 1",
    "vehicleType": "Race Car",
    "popularity": 90,
    "packagingType": "Display clamshell case",
    "color": "rosso-corsa"
  },
  {
    "name": "Tarmac Works Subaru Impreza WRC 1998 Rally Monte Carlo",
    "brand": "Tarmac Works",
    "category": "Premium",
    "subcategory": "Motorsport",
    "price": 1629,
    "stockStatus": "In Stock",
    "scale": "1:64",
    "imported": true,
    "carded": false,
    "series": "Motorsport",
    "releaseYear": 2024,
    "wave": "Drop 8",
    "vehicleType": "Race Car",
    "popularity": 85,
    "packagingType": "Collector display box",
    "color": "rally-blue"
  },
  {
    "name": "Tarmac Works Pagani Zonda Revolucion Carbon",
    "brand": "Tarmac Works",
    "category": "Limited Edition",
    "subcategory": "Hobby64",
    "price": 2299,
    "stockStatus": "Pre-order",
    "scale": "1:64",
    "imported": true,
    "carded": false,
    "series": "Hobby64",
    "releaseYear": 2025,
    "wave": "Drop 3",
    "vehicleType": "Supercar",
    "popularity": 92,
    "packagingType": "Premium acrylic case",
    "color": "carbon-silver"
  },
  {
    "name": "Kaido House Datsun 510 Wagon Hanami V1",
    "brand": "Kaido House",
    "category": "Limited Edition",
    "subcategory": "Kaido House",
    "price": 1899,
    "stockStatus": "In Stock",
    "scale": "1:64",
    "imported": true,
    "carded": false,
    "series": "Kaido House",
    "releaseYear": 2024,
    "wave": "Series 3",
    "vehicleType": "JDM",
    "featured": true,
    "popularity": 95,
    "packagingType": "Kaido collector blister box",
    "color": "sakura-pink"
  },
  {
    "name": "Kaido House Mini GT NSX Kaido Works",
    "brand": "Kaido House",
    "category": "Imported",
    "subcategory": "Kaido House",
    "price": 1849,
    "stockStatus": "In Stock",
    "scale": "1:64",
    "imported": true,
    "carded": false,
    "series": "Kaido House",
    "releaseYear": 2024,
    "wave": "Series 4",
    "vehicleType": "JDM",
    "popularity": 91,
    "packagingType": "Kaido collector blister box",
    "color": "ultra-blue"
  },
  {
    "name": "Kaido House Fairlady Z Kaido Street Fighter",
    "brand": "Kaido House",
    "category": "Premium",
    "subcategory": "Kaido House",
    "price": 1799,
    "stockStatus": "In Stock",
    "scale": "1:64",
    "imported": true,
    "carded": false,
    "series": "Kaido House",
    "releaseYear": 2024,
    "wave": "Series 5",
    "vehicleType": "JDM",
    "popularity": 88,
    "packagingType": "Kaido collector blister box",
    "color": "burnt-orange"
  },
  {
    "name": "Kaido House BRE Datsun 510 Pro Street",
    "brand": "Kaido House",
    "category": "Collector Set",
    "subcategory": "Kaido House",
    "price": 1949,
    "stockStatus": "Sold Out",
    "scale": "1:64",
    "imported": true,
    "carded": false,
    "series": "Kaido House",
    "releaseYear": 2023,
    "wave": "Series 2",
    "vehicleType": "Race Car",
    "popularity": 89,
    "packagingType": "Kaido collector blister box",
    "color": "bre-white"
  },
  {
    "name": "Kaido House Civic EF Kanjo Night Runner",
    "brand": "Kaido House",
    "category": "Pre-order",
    "subcategory": "Kaido House",
    "price": 1899,
    "stockStatus": "Pre-order",
    "scale": "1:64",
    "imported": true,
    "carded": false,
    "series": "Kaido House",
    "releaseYear": 2025,
    "wave": "Series 1",
    "vehicleType": "JDM",
    "popularity": 90,
    "packagingType": "Kaido collector blister box",
    "color": "kanjo-black"
  },
  {
    "name": "Kaido House Silverado Lowrider Shop Truck",
    "brand": "Kaido House",
    "category": "Imported",
    "subcategory": "Kaido House",
    "price": 1869,
    "stockStatus": "In Stock",
    "scale": "1:64",
    "imported": true,
    "carded": false,
    "series": "Kaido House",
    "releaseYear": 2024,
    "wave": "Series 4",
    "vehicleType": "SUV / Truck",
    "popularity": 84,
    "packagingType": "Kaido collector blister box",
    "color": "shop-blue"
  },
  {
    "name": "Kaido House Skyline C210 Bosozoku Edition",
    "brand": "Kaido House",
    "category": "Limited Edition",
    "subcategory": "Kaido House",
    "price": 1969,
    "stockStatus": "Pre-order",
    "scale": "1:64",
    "imported": true,
    "carded": false,
    "series": "Kaido House",
    "releaseYear": 2025,
    "wave": "Series 2",
    "vehicleType": "JDM",
    "popularity": 94,
    "packagingType": "Kaido collector blister box",
    "color": "bosozoku-red"
  },
  {
    "name": "Kaido House Corvette C3 Widebody Drag Spec",
    "brand": "Kaido House",
    "category": "Premium",
    "subcategory": "Kaido House",
    "price": 1819,
    "stockStatus": "In Stock",
    "scale": "1:64",
    "imported": true,
    "carded": false,
    "series": "Kaido House",
    "releaseYear": 2024,
    "wave": "Series 3",
    "vehicleType": "Muscle",
    "popularity": 82,
    "packagingType": "Kaido collector blister box",
    "color": "chrome-silver"
  },
  {
    "name": "Hot Wheels Pre-order Ferrari 499P Le Mans Winner",
    "brand": "Hot Wheels",
    "category": "Pre-order",
    "subcategory": "Motorsport",
    "price": 999,
    "stockStatus": "Pre-order",
    "scale": "1:64",
    "imported": true,
    "carded": true,
    "series": "Motorsport",
    "releaseYear": 2025,
    "wave": "Wave 1",
    "vehicleType": "Race Car",
    "popularity": 91,
    "packagingType": "Carded premium blister",
    "color": "scarlet-red"
  },
  {
    "name": "Matchbox Collectors Land Rover Defender 90 Camel Trophy",
    "brand": "Matchbox",
    "category": "Imported",
    "subcategory": "Collectors",
    "price": 829,
    "stockStatus": "In Stock",
    "scale": "1:64",
    "imported": true,
    "carded": true,
    "series": "Collectors",
    "releaseYear": 2024,
    "wave": "Wave 2",
    "vehicleType": "SUV / Truck",
    "popularity": 82,
    "packagingType": "Carded collector blister",
    "color": "camel-sand"
  },
  {
    "name": "Majorette Volkswagen T1 Vintage Surf Bus",
    "brand": "Majorette",
    "category": "Mainline",
    "subcategory": "Vintage",
    "price": 299,
    "stockStatus": "In Stock",
    "scale": "1:64",
    "imported": false,
    "carded": true,
    "series": "Vintage",
    "releaseYear": 2024,
    "wave": "Wave 4",
    "vehicleType": "Classic",
    "popularity": 67,
    "packagingType": "Carded blister",
    "color": "surf-blue"
  },
  {
    "name": "Mini GT Alfa Romeo Giulia GTAm Rosso GTA",
    "brand": "Mini GT",
    "category": "Premium",
    "subcategory": "Street",
    "price": 1469,
    "stockStatus": "In Stock",
    "scale": "1:64",
    "imported": true,
    "carded": false,
    "series": "Street",
    "releaseYear": 2024,
    "wave": "Drop 7",
    "vehicleType": "Supercar",
    "popularity": 83,
    "packagingType": "Mini GT window box",
    "color": "rosso-gta"
  },
  {
    "name": "Pop Race Mazda RX-7 RE-Amemiya Widebody",
    "brand": "Pop Race",
    "category": "Imported",
    "subcategory": "Street Tuner",
    "price": 1459,
    "stockStatus": "In Stock",
    "scale": "1:64",
    "imported": true,
    "carded": false,
    "series": "Street Tuner",
    "releaseYear": 2024,
    "wave": "Series 4",
    "vehicleType": "JDM",
    "popularity": 87,
    "packagingType": "Collector display box",
    "color": "amemiya-yellow"
  },
  {
    "name": "Tarmac Works Porsche 911 RSR Pink Pig",
    "brand": "Tarmac Works",
    "category": "Premium",
    "subcategory": "Motorsport",
    "price": 1679,
    "stockStatus": "In Stock",
    "scale": "1:64",
    "imported": true,
    "carded": false,
    "series": "Motorsport",
    "releaseYear": 2024,
    "wave": "Drop 9",
    "vehicleType": "Race Car",
    "popularity": 86,
    "packagingType": "Collector display box",
    "color": "pink-pig"
  },
  {
    "name": "Kaido House Alfa Romeo GTV Widebody Sprint",
    "brand": "Kaido House",
    "category": "Imported",
    "subcategory": "Kaido House",
    "price": 1829,
    "stockStatus": "In Stock",
    "scale": "1:64",
    "imported": true,
    "carded": false,
    "series": "Kaido House",
    "releaseYear": 2024,
    "wave": "Series 5",
    "vehicleType": "Classic",
    "popularity": 80,
    "packagingType": "Kaido collector blister box",
    "color": "italia-green"
  }
]